Metadata-Version: 2.1
Name: rightpad
Version: 0.1.0
Summary: A port of the infamous right-pad npm package
Home-page: https://github.com/mariekodes/rightpad
Author: Marie Kodes
Author-email: mariekodes@gmail.com
Classifier: Programming Language :: Python :: 3
Classifier: Operating System :: OS Independent
License-File: LICENSE
